cratedb_sqlparse/AstBuilder.py
cratedb_sqlparse/__init__.py
cratedb_sqlparse/models.py
cratedb_sqlparse/parser.py
cratedb_sqlparse/generated_parser/AbstractSqlBaseLexer.py
cratedb_sqlparse/generated_parser/SqlBaseLexer.py
cratedb_sqlparse/generated_parser/SqlBaseParser.py
cratedb_sqlparse/generated_parser/SqlBaseParserListener.py
cratedb_sqlparse/generated_parser/SqlBaseParserVisitor.py
cratedb_sqlparse/generated_parser/__init__.py
tests/__init__.py
tests/conftest.py
tests/test_enricher.py
tests/test_exceptions.py
tests/test_lexer.py
cratedb_sqlparse-0.0.17.dist-info/METADATA
cratedb_sqlparse-0.0.17.dist-info/WHEEL
cratedb_sqlparse-0.0.17.dist-info/top_level.txt
cratedb_sqlparse-0.0.17.dist-info/RECORD
