Metadata-Version: 2.4
Name: cratedb-sqlparse
Version: 0.0.17
Summary: Parsing utilities to validate and split SQL statements for CrateDB.
Author-email: Ivan Sanchez Valencia <ivan.sanchezvalencia@crate.io>
License: Apache License 2.0
Project-URL: Changelog, https://github.com/crate/cratedb-sqlparse/releases
Project-URL: Documentation, https://github.com/crate/cratedb-sqlparse
Project-URL: Homepage, https://github.com/crate/cratedb-sqlparse
Project-URL: Repository, https://github.com/crate/cratedb-sqlparse
Keywords: antlr4,antlr4 grammar,cratedb,grammar,sql,sql grammar,sql parser,sql parsing
Classifier: Development Status :: 3 - Alpha
Classifier: Environment :: Console
Classifier: Intended Audience :: Customer Service
Classifier: Intended Audience :: Developers
Classifier: Intended Audience :: Education
Classifier: Intended Audience :: End Users/Desktop
Classifier: Intended Audience :: Information Technology
Classifier: Intended Audience :: Science/Research
Classifier: Intended Audience :: Telecommunications Industry
Classifier: License :: OSI Approved :: Apache Software License
Classifier: Operating System :: MacOS :: MacOS X
Classifier: Operating System :: Microsoft :: Windows
Classifier: Operating System :: POSIX :: Linux
Classifier: Operating System :: Unix
Classifier: Programming Language :: Python
Classifier: Programming Language :: Python :: 3 :: Only
Classifier: Programming Language :: Python :: 3.9
Classifier: Programming Language :: Python :: 3.10
Classifier: Programming Language :: Python :: 3.11
Classifier: Programming Language :: Python :: 3.12
Classifier: Programming Language :: Python :: 3.13
Classifier: Programming Language :: SQL
Classifier: Topic :: Communications
Classifier: Topic :: Database
Classifier: Topic :: Documentation
Classifier: Topic :: Education
Classifier: Topic :: Office/Business
Classifier: Topic :: Scientific/Engineering
Classifier: Topic :: Software Development :: Libraries
Classifier: Topic :: Software Development :: Testing
Classifier: Topic :: System :: Archiving
Classifier: Topic :: System :: Systems Administration
Classifier: Topic :: Text Processing
Classifier: Topic :: Utilities
Requires-Python: >=3.9
Requires-Dist: antlr4-python3-runtime<4.14
